apx_fractal_task_collection/__FRACTAL_MANIFEST__.json
apx_fractal_task_collection/__init__.py
apx_fractal_task_collection/init_utils.py
apx_fractal_task_collection/io_models.py
apx_fractal_task_collection/utils.py
apx_fractal_task_collection/dev/__init__.py
apx_fractal_task_collection/dev/task_list.py
apx_fractal_task_collection/features/__init__.py
apx_fractal_task_collection/features/intensity.py
apx_fractal_task_collection/features/morphology.py
apx_fractal_task_collection/features/population.py
apx_fractal_task_collection/features/texture.py
apx_fractal_task_collection/tasks/__init__.py
apx_fractal_task_collection/tasks/aggregate_feature_tables.py
apx_fractal_task_collection/tasks/apply_basicpy_illumination_models.py
apx_fractal_task_collection/tasks/ashlar_stitching_and_registration.py
apx_fractal_task_collection/tasks/calculate_basicpy_illumination_models.py
apx_fractal_task_collection/tasks/calculate_pixel_intensity_correlation.py
apx_fractal_task_collection/tasks/clip_label_image.py
apx_fractal_task_collection/tasks/convert_IC6000_to_ome_zarr.py
apx_fractal_task_collection/tasks/convert_channel_to_label.py
apx_fractal_task_collection/tasks/correct_4i_bleaching_artifacts.py
apx_fractal_task_collection/tasks/correct_chromatic_shift.py
apx_fractal_task_collection/tasks/detect_blob_centroids.py
apx_fractal_task_collection/tasks/expand_labels_skimage.py
apx_fractal_task_collection/tasks/filter_label_by_size.py
apx_fractal_task_collection/tasks/init_add_multiplexing_cycle_IC6000.py
apx_fractal_task_collection/tasks/init_aggregate_feature_tables.py
apx_fractal_task_collection/tasks/init_ashlar_stitching_and_registration.py
apx_fractal_task_collection/tasks/init_calculate_basicpy_illumination_models.py
apx_fractal_task_collection/tasks/init_calculate_pixel_intensity_correlation.py
apx_fractal_task_collection/tasks/init_clip_label_image.py
apx_fractal_task_collection/tasks/init_convert_IC6000_to_ome_zarr.py
apx_fractal_task_collection-0.4.12.dist-info/licenses/LICENSE
apx_fractal_task_collection-0.4.12.dist-info/METADATA
apx_fractal_task_collection-0.4.12.dist-info/WHEEL
apx_fractal_task_collection-0.4.12.dist-info/top_level.txt
apx_fractal_task_collection-0.4.12.dist-info/RECORD
