Metadata-Version: 2.4
Name: apx-fractal-task-collection
Version: 0.4.12
Summary: A collection of custom fractal tasks.
Author-email: Adrian Tschan <atschan@apricotx.com>
License: BSD-3-Clause
Requires-Python: >=3.11
License-File: LICENSE
Requires-Dist: fractal-tasks-core==1.4.3
Requires-Dist: scikit-image
Requires-Dist: matplotlib
Requires-Dist: image_registration
Requires-Dist: pytest
Requires-Dist: mahotas
Requires-Dist: basicpy
Requires-Dist: minisom
Requires-Dist: phenograph
Requires-Dist: scikit-learn<1.7
Requires-Dist: tifffile==2025.1.10
Requires-Dist: jax==0.4.23
Requires-Dist: jaxlib==0.4.23
Requires-Dist: SimpleITK-SimpleElastix
Requires-Dist: ome-zarr
Requires-Dist: ashlar
Requires-Dist: pyfeats
Requires-Dist: pydantic<2.8.0,>=2.0
Requires-Dist: defusedxml
Requires-Dist: seaborn
Requires-Dist: numcodecs==0.13.1
Requires-Dist: fractal-task-tools==0.1.0
Requires-Dist: hyperactive==4.8.0
Requires-Dist: dask==2024.2.0
Requires-Dist: zarr==2.17.0
Requires-Dist: numpy<2
Requires-Dist: ml-dtypes==0.5.1
Requires-Dist: h5py==3.14.0
Requires-Dist: PyWavelets<=1.5.0
Requires-Dist: pandas<2.0.0
Requires-Dist: contourpy<=1.2.0
Requires-Dist: leidenalg==0.10.2
Provides-Extra: dev
Requires-Dist: devtools; extra == "dev"
Requires-Dist: pytest; extra == "dev"
Requires-Dist: requests; extra == "dev"
Requires-Dist: build; extra == "dev"
Requires-Dist: jsonschema; extra == "dev"
Requires-Dist: mkdocs; extra == "dev"
Requires-Dist: mkdocstrings; extra == "dev"
Requires-Dist: mkdocs-gen-files; extra == "dev"
Requires-Dist: mkdocs-material; extra == "dev"
Requires-Dist: mkdocs-material-extensions; extra == "dev"
Requires-Dist: mkdocstrings; extra == "dev"
Requires-Dist: mkdocstrings-python; extra == "dev"
Requires-Dist: bumpver; extra == "dev"
Dynamic: license-file
